[
  {
    "path": "/",
    "concurrency": 10,
    "totalRequests": 600,
    "elapsedSec": 24.44,
    "rps": 24.55,
    "errorRate": 0,
    "latencyMs": {
      "avg": 403.46,
      "p50": 381.51,
      "p90": 508.81,
      "p95": 572.7,
      "p99": 784.83,
      "max": 915.57
    },
    "statuses": {
      "200": 600
    }
  },
  {
    "path": "/",
    "concurrency": 25,
    "totalRequests": 1500,
    "elapsedSec": 50.76,
    "rps": 29.55,
    "errorRate": 0,
    "latencyMs": {
      "avg": 842.01,
      "p50": 797.79,
      "p90": 1033.12,
      "p95": 1104.89,
      "p99": 1580.63,
      "max": 1986.35
    },
    "statuses": {
      "200": 1500
    }
  },
  {
    "path": "/",
    "concurrency": 50,
    "totalRequests": 3000,
    "elapsedSec": 113.17,
    "rps": 26.51,
    "errorRate": 0,
    "latencyMs": {
      "avg": 1868.97,
      "p50": 1798.53,
      "p90": 2318.15,
      "p95": 2579.59,
      "p99": 3172.26,
      "max": 3720.09
    },
    "statuses": {
      "200": 3000
    }
  },
  {
    "path": "/web-stories",
    "concurrency": 25,
    "totalRequests": 1500,
    "elapsedSec": 32.62,
    "rps": 45.98,
    "errorRate": 0,
    "latencyMs": {
      "avg": 541.54,
      "p50": 519.29,
      "p90": 620.95,
      "p95": 664.72,
      "p99": 1043.79,
      "max": 1081.1
    },
    "statuses": {
      "200": 1500
    }
  },
  {
    "path": "/search?q=india",
    "concurrency": 25,
    "totalRequests": 1500,
    "elapsedSec": 29.11,
    "rps": 51.52,
    "errorRate": 0,
    "latencyMs": {
      "avg": 482.23,
      "p50": 471.95,
      "p90": 554.12,
      "p95": 596.45,
      "p99": 706.49,
      "max": 899.43
    },
    "statuses": {
      "200": 1500
    }
  }
]
